pymovavg/__init__.py
pymovavg/movavg.py
pymovavg-0.2.dist-info/LICENSE
pymovavg-0.2.dist-info/METADATA
pymovavg-0.2.dist-info/WHEEL
pymovavg-0.2.dist-info/top_level.txt
pymovavg-0.2.dist-info/RECORD
